kubesys/__init__.py
kubesys/analyzer.py
kubesys/client.py
kubesys/common.py
kubesys/http_request.py
kubesys/watch_handler.py
kubesys/watcher.py
kubesys-1.0.7.dist-info/LICENSE
kubesys-1.0.7.dist-info/METADATA
kubesys-1.0.7.dist-info/WHEEL
kubesys-1.0.7.dist-info/top_level.txt
kubesys-1.0.7.dist-info/RECORD
