Metadata-Version: 2.1
Name: kubesys
Version: 1.0.7
Summary: a python-based wrapper library for kubernetes-calls
Home-page: UNKNOWN
Author: a_flying_fish
Author-email: a_flying_fish@outlook.com
License: MIT
Keywords: k8s
Platform: UNKNOWN
Requires-Dist: requests (>=0.0.0)
